{
  "blocks": [
    {
      "vector": {
        "x": -1.0,
        "y": -1.0,
        "z": -1.0
      },
      "data": "minecraft:purpur_block"
    },
    {
      "vector": {
        "x": -1.0,
        "y": -1.0,
        "z": 1.0
      },
      "data": "minecraft:purpur_block"
    },
    {
      "vector": {
        "x": 0.0,
        "y": -1.0,
        "z": 0.0
      },
      "data": "minecraft:sea_lantern"
    },
    {
      "vector": {
        "x": 1.0,
        "y": -1.0,
        "z": -1.0
      },
      "data": "minecraft:purpur_block"
    },
    {
      "vector": {
        "x": 1.0,
        "y": -1.0,
        "z": 1.0
      },
      "data": "minecraft:purpur_block"
    },
    {
      "vector": {
        "x": -1.0,
        "y": -1.0,
        "z": 0.0
      },
      "data": "minecraft:purpur_stairs[facing=west]"
    },
    {
      "vector": {
        "x": 0.0,
        "y": -1.0,
        "z": -1.0
      },
      "data": "minecraft:purpur_stairs[facing=north]"
    },
    {
      "vector": {
        "x": 0.0,
        "y": -1.0,
        "z": 1.0
      },
      "data": "minecraft:purpur_stairs[facing=south]"
    },
    {
      "vector": {
        "x": 1.0,
        "y": -1.0,
        "z": 0.0
      },
      "data": "minecraft:purpur_stairs[facing=east]"
    }
  ]
}